cerebrum/__init__.py
cerebrum/agents/base.py
cerebrum/client/__init__.py
cerebrum/interface/__init__.py
cerebrum/llm/communication.py
cerebrum/llm/layer.py
cerebrum/manager/__init__.py
cerebrum/manager/agent.py
cerebrum/manager/package.py
cerebrum/manager/tool.py
cerebrum/memory/__init__.py
cerebrum/memory/communication.py
cerebrum/memory/layer.py
cerebrum/overrides/layer.py
cerebrum/runtime/__init__.py
cerebrum/runtime/process.py
cerebrum/storage/communication.py
cerebrum/storage/layer.py
cerebrum/tool/base.py
cerebrum/tool/communication.py
cerebrum/tool/layer.py
cerebrum/tool/core/__init__.py
cerebrum/tool/core/registry.py
cerebrum/tool/core/bing/bing_search.py
cerebrum/tool/core/currency_converter/currency_converter.py
cerebrum/tool/core/file/__init__.py
cerebrum/tool/core/file/downloader.py
cerebrum/tool/core/google/google_places.py
cerebrum/tool/core/google/google_search.py
cerebrum/tool/core/imdb/top_movies.py
cerebrum/tool/core/imdb/top_series.py
cerebrum/tool/core/impira/doc_question_answering.py
cerebrum/tool/core/meteosource_weather/find_place.py
cerebrum/tool/core/moonphase/moon_phase_search.py
cerebrum/tool/core/openai/speech_to_text.py
cerebrum/tool/core/shazam/song_auto_complete.py
cerebrum/tool/core/stability-ai/text_to_image.py
cerebrum/tool/core/suno/text_to_speech.py
cerebrum/tool/core/timbrooks/image_to_image.py
cerebrum/tool/core/transcriber/transcriber.py
cerebrum/tool/core/travel_planner/accommodations.py
cerebrum/tool/core/travel_planner/attractions.py
cerebrum/tool/core/travel_planner/cities.py
cerebrum/tool/core/travel_planner/flights.py
cerebrum/tool/core/travel_planner/google_distance_matrix.py
cerebrum/tool/core/travel_planner/notebook.py
cerebrum/tool/core/travel_planner/planner.py
cerebrum/tool/core/travel_planner/restaurants.py
cerebrum/tool/core/trip_advisor/airport_search.py
cerebrum/tool/core/trip_advisor/flight_search.py
cerebrum/tool/core/trip_advisor/get_hotel_details.py
cerebrum/tool/core/trip_advisor/get_restaurant_details.py
aios_agent_sdk-0.0.3.dist-info/METADATA
aios_agent_sdk-0.0.3.dist-info/WHEEL
aios_agent_sdk-0.0.3.dist-info/entry_points.txt
aios_agent_sdk-0.0.3.dist-info/licenses/LICENSE
aios_agent_sdk-0.0.3.dist-info/RECORD
