Metadata-Version: 2.3
Name: aios-agent-sdk
Version: 0.0.3
Summary: Cerebrum: Agent SDK for AIOS
Project-URL: Homepage, https://github.com/agiresearch/Cerebrum
Project-URL: Repository, https://github.com/agiresearch/Cerebrum.git
License: MIT License
Keywords: agi,aios,cerebrum,llm,os
Classifier: Development Status :: 3 - Alpha
Classifier: Intended Audience :: Developers
Classifier: License :: OSI Approved :: MIT License
Classifier: Programming Language :: Python :: 3
Classifier: Programming Language :: Python :: 3.10
Classifier: Programming Language :: Python :: 3.11
Classifier: Topic :: Software Development :: Libraries :: Python Modules
Requires-Python: <3.12,>=3.10
Requires-Dist: platformdirs
Requires-Dist: pydantic
Requires-Dist: requests
